{
    "visitReport10": {
        "name": "Visit Report",
        "type": "visits",
        "config": {
            "forDataAnalysis": false,
            "patientAttributes": [
                "PhoneNumber"
            ],
            "visitAttributes": [
               "Admission Status"
            ],
            "patientAddresses": [
                "Address3",
                "City_Village"
            ],
            "applyDateRangeFor": "visitStartDate",
            "visitTypesToFilter": [
                "IPD",
                "OPD",
                "EMERGENCY"
            ]
        }
    },
    "visitReport11": {
        "name": "List of Registered Patients",
        "type": "MRSGeneric",
        "config": {
          "sqlPath": "/var/www/bahmni_config/openmrs/apps/reports/sql/ListofRegPatient.sql"
    
      }
     },
     "otReport": {
        "name": "List of Patients with Operations/surgeries statuses in the selected date range",
        "type": "MRSGeneric",
        "config": {
          "sqlPath": "/var/www/bahmni_config/openmrs/apps/reports/sql/ListofOTpatient.sql"
    
      }
     },
     "diagnosisCountReport": {
        "name": "Count of Diagnosis",
        "type": "MRSGeneric",
        "config": {
          "sqlPath": "/var/www/bahmni_config/openmrs/apps/reports/sql/DiagnosisCount.sql"
    
}
},

"missedAppointmentReport": {
        "name": "List of Patients with Missed Appointment",
        "type": "MRSGeneric",
        "config": {
          "sqlPath": "/var/www/bahmni_config/openmrs/apps/reports/sql/missedAppointment.sql"
        }
    },
    
    "chiefComplaintReport": {
        "name": "Chief Complaint Report",
        "type": "obsCount",
        "config": {
            "ageGroupName": "All Ages",
            "conceptNames": [
                "Chief Complaint"
            ],
            "countOnlyClosedVisits": "false",
            "visitTypes": [
                "IPD",
                "OPD"
            ]
        }
    },
    "inpatientMorbidity": {
        "name": "Inpatient Morbidity",
        "type": "diagnosisCount",
        "config": {
            "visitTypes": [
                "IPD"
            ]
        }
    },
    "outpatientMorbidity": {
        "name": "Outpatient Morbidity",
        "type": "diagnosisCount",
        "config": {
            "visitTypes": [
                "OPD"
            ]
        }
    },
    
    "genericLaboratoryServices": {
        "name": "Laboratory Services",
        "type": "ElisGeneric",
        "config": {
            "sqlPath": "/var/www/bahmni_config/openmrs/apps/reports/sql/testCount.sql"
        }
    },
    
    "OPD/IPDVisitCount": {
        "name": "OPD/IPD Visit Count",
        "type": "IpdOpdVisitCount"
    },
    
    "radiology(X-Ray)Count": {
        "name": "Radiology(X-Ray) Count",
        "type": "ObsCountByConceptClass",
        "config": {
            "conceptClassNames": [
                "Radiology"
            ]
        }
    },
   
    "IPDPatientsReport": {
        "name": "IPD Patients Report",
        "type": "ipdPatients",
        "config": {
            "addressAttributes": [
                "address1",
                "city_village"
            ],
            "patientAttributes": [
                "caste",
                "education"
            ],
            "conceptNames": [
                "Height",
                "Weight"
            ],
            "filterBy": "Date of Discharge"
        }
    },
    
    "patientsProgramStateCountReport": {
        "name": "Patients HIV Program State Count Report",
        "type": "programStateCount",
        "config": {
            "programName": "HIV Program"
        }
    },

    "patientsTbProgramStateCountReport": {
        "name": "Patients TB Program State Count Report",
        "type": "programStateCount",
        "config": {
            "programName": "TB Program"
        }
    },

    "programPatientStateReport": {
        "name": "HIV Program Patient State Report",
        "type": "PatientProgramReport",
        "config": {
            "programName": "HIV Program"
        }
    },

    "programTbPatientStateReport": {
        "name": "TB Program Patient State Report",
        "type": "PatientProgramReport",
        "config": {
            "programName": "TB Program"
        }
    },

    "programStateTransitionReport": {
        "name": "HIV Program State Transition Report",
        "type": "programStateTransitionReport",
        "config": {
            "programName": "HIV Program"
        }
    },

    "programTbStateTransitionReport": {
        "name": "TB Program State Transition Report",
        "type": "programStateTransitionReport",
        "config": {
            "programName": "TB Program"
        }
    },
   
    "drugOrderReport": {
        "name": "Drug Order report",
        "type": "DrugOrder"
    },
    "SampleGenericProgramReport": {
        "name": "List of Patient registered in Programs",
        "type": "programs",
        "config": {
            "patientAttributes": [
                "education",
                "primaryContact",
                "secondaryContact",
                "class",
                "cluster"
            ],
            "patientAddresses": [
                "city_village",
                "address3"
            ],
            "programAttributes": [],
            "forDataAnalysis": true,
            "showAllStates": true,
            "programNamesToFilter": [
                "HIV Program",
                "TB Program"
            ]
        }
    },
   "GenericLabOrderReportAggregation": {
    "name": "Lab Orders Disaggregated by Gender",
    "type": "aggregation",
    "config": {
      "report": {
        "type": "labOrders",
        "config": {
          "forDataAnalysis": true,
          "showVisitInfo": true
        }
      },
      "rowGroups": [
        "Test Name"
      ],
      "columnGroups": [
        "Gender"
      ],
      "distinctGroups": [
        "Patient Identifier"
      ]
    }
  }
}
